aird/__init__.py
aird/__main__.py
aird/main.py
aird/templates/admin.html
aird/templates/admin_ldap.html
aird/templates/admin_login.html
aird/templates/admin_users.html
aird/templates/browse.html
aird/templates/directory.html
aird/templates/edit.html
aird/templates/error.html
aird/templates/file.html
aird/templates/ldap_config_create.html
aird/templates/ldap_config_edit.html
aird/templates/login.html
aird/templates/profile.html
aird/templates/share.html
aird/templates/shared_list.html
aird/templates/super_search.html
aird/templates/token_verification.html
aird/templates/user_create.html
aird/templates/user_edit.html
aird-0.4.5.dist-info/licenses/LICENSE
tests/__init__.py
tests/test_additional_utilities.py
tests/test_api_handlers.py
tests/test_database.py
tests/test_file_operations.py
tests/test_file_streaming.py
tests/test_filter_expression.py
tests/test_handlers.py
tests/test_ldap_handlers.py
tests/test_main_coverage.py
tests/test_mmap_handler.py
tests/test_utilities.py
tests/test_websocket_handlers.py
aird-0.4.5.dist-info/METADATA
aird-0.4.5.dist-info/WHEEL
aird-0.4.5.dist-info/entry_points.txt
aird-0.4.5.dist-info/top_level.txt
aird-0.4.5.dist-info/RECORD
