Metadata-Version: 2.4
Name: aird
Version: 0.4.5
Summary: Aird - A lightweight web-based file browser, editor, and streamer with real-time capabilities
Home-page: https://github.com/blinkerbit/aird
Author: Viswantha Srinivas P
Author-email: psviswanatha@gmail.com
License: Custom
Classifier: Programming Language :: Python :: 3
Classifier: License :: Other/Proprietary License
Classifier: Operating System :: OS Independent
Requires-Python: >=3.10
License-File: LICENSE
Requires-Dist: tornado>=6.5.1
Requires-Dist: ldap3>=2.9.1
Requires-Dist: aiofiles>=23.0.0
Requires-Dist: argon2-cffi>=23.1.0
Provides-Extra: test
Requires-Dist: pytest>=8.3.3; extra == "test"
Requires-Dist: pytest-asyncio>=0.25.0; extra == "test"
Requires-Dist: pytest-mock>=3.14.0; extra == "test"
Requires-Dist: pytest-cov>=6.0.0; extra == "test"
Requires-Dist: pytest-tornado>=0.8.1; extra == "test"
Requires-Dist: coverage>=7.6.9; extra == "test"
Requires-Dist: mock>=5.1.0; extra == "test"
Dynamic: author
Dynamic: author-email
Dynamic: classifier
Dynamic: description
Dynamic: description-content-type
Dynamic: home-page
Dynamic: license
Dynamic: license-file
Dynamic: provides-extra
Dynamic: requires-dist
Dynamic: requires-python
Dynamic: summary
